cocoon_data/__init__.py
cocoon_data/app.py
cocoon_data/cli.py
cocoon_data/config.py
cocoon_data/constant.py
cocoon_data/data_type.py
cocoon_data/database.py
cocoon_data/extract.py
cocoon_data/file_sys.py
cocoon_data/llm.py
cocoon_data/utils.py
cocoon_data/viz.py
cocoon_data/widgets.py
cocoon_data/workflow.py
cocoon_data-0.1.197.dist-info/LICENSE
cocoon_data-0.1.197.dist-info/METADATA
cocoon_data-0.1.197.dist-info/WHEEL
cocoon_data-0.1.197.dist-info/entry_points.txt
cocoon_data-0.1.197.dist-info/top_level.txt
cocoon_data-0.1.197.dist-info/RECORD
