Metadata-Version: 2.1
Name: cocoon_data
Version: 0.1.197
Summary: Cocoon is an open-source project that aims to free analysts from tedious data transformations with LLM.
Home-page: https://github.com/Cocoon-Data-Transformation/cocoon/
Author: Zachary Huang
Author-email: zh2408@columbia.edu
License-File: LICENSE
Requires-Dist: faiss-cpu
Requires-Dist: graphviz
Requires-Dist: ipywidgets
Requires-Dist: matplotlib
Requires-Dist: networkx
Requires-Dist: numpy
Requires-Dist: openai
Requires-Dist: anthropic
Requires-Dist: pandas
Requires-Dist: seaborn
Requires-Dist: tqdm
Requires-Dist: duckdb
Requires-Dist: snowflake-connector-python
Requires-Dist: matplotlib-venn
Requires-Dist: scipy
Requires-Dist: chardet
Requires-Dist: openpyxl
Requires-Dist: xlrd
Requires-Dist: datasketch
Requires-Dist: bs4
Requires-Dist: jinja2
Requires-Dist: boto3
Requires-Dist: pyodbc
Requires-Dist: sqlglot
Requires-Dist: ruamel.yaml
Requires-Dist: db-dtypes
Requires-Dist: google-cloud-bigquery
Requires-Dist: streamlit
Requires-Dist: tiktoken
Provides-Extra: geo
Requires-Dist: geopandas==0.14.1; extra == "geo"
Requires-Dist: rasterio; extra == "geo"
Requires-Dist: pyproj; extra == "geo"
Requires-Dist: shapely; extra == "geo"
Requires-Dist: scipy; extra == "geo"
